aiowerobot/__init__.py
aiowerobot/__version__.py
aiowerobot/client.py
aiowerobot/config.py
aiowerobot/exceptions.py
aiowerobot/logger.py
aiowerobot/parser.py
aiowerobot/pay.py
aiowerobot/replies.py
aiowerobot/robot.py
aiowerobot/testing.py
aiowerobot/utils.py
aiowerobot/crypto/__init__.py
aiowerobot/crypto/exceptions.py
aiowerobot/crypto/pkcs7.py
aiowerobot/messages/__init__.py
aiowerobot/messages/base.py
aiowerobot/messages/entries.py
aiowerobot/messages/events.py
aiowerobot/messages/messages.py
aiowerobot/session/__init__.py
aiowerobot/session/filestorage.py
aiowerobot/session/sqlitestorage.py
aiowerobot-0.0.9.dist-info/METADATA
aiowerobot-0.0.9.dist-info/WHEEL
aiowerobot-0.0.9.dist-info/top_level.txt
aiowerobot-0.0.9.dist-info/RECORD
