Metadata-Version: 2.1
Name: aiowerobot
Version: 0.0.9
Summary: 一个基础sanic的异步微信公众号开发框架
Home-page: https://github.com/linzhiming0826/aiowerobot
Author: TuoX
Author-email: 120549827@qq.com
License: MIT
Platform: any
Classifier: Programming Language :: Python :: 3.6
Classifier: Programming Language :: Python :: 3.7
Classifier: License :: OSI Approved :: MIT License
Requires-Dist: sanic (>=22.9.1)
Requires-Dist: xmltodict (>=0.12.0)
Requires-Dist: aiohttp (>=3.6.2)
